de/__init__.py
de/cms.py
de/hm.py
de/utils/__init__.py
de/utils/cms_utils.py
de/utils/hm_utils.py
hcmp_de-1.0.3.dist-info/METADATA
hcmp_de-1.0.3.dist-info/WHEEL
hcmp_de-1.0.3.dist-info/top_level.txt
hcmp_de-1.0.3.dist-info/RECORD
