Metadata-Version: 2.1
Name: hcmp-de
Version: 1.0.3
Summary: Internal Data Engineering utility tool
Home-page: https://github.com/fin1te/
Author: Rishabh Mehta
Author-email: Rishabh2.Mehta@ril.com
Requires-Dist: requests
Requires-Dist: loguru
Requires-Dist: pycryptodome
Requires-Dist: setuptools
Requires-Dist: confluent-kafka
